Metadata-Version: 2.1
Name: Trading212
Version: 0.1.6
Summary: This package is an unofficial API for Trading212.
Home-page: https://github.com/BenTimor/Trading212API/
Author: Ben Timor
Author-email: me@bentimor.com
License: MIT
Download-URL: https://github.com/BenTimor/Trading212API/archive/0.1.5.tar.gz
Keywords: trading,trading212,stocks,money,api
Platform: UNKNOWN
Classifier: Intended Audience :: Developers
Classifier: Topic :: Software Development :: Build Tools
Classifier: License :: OSI Approved :: MIT License
Classifier: Programming Language :: Python :: 3
Classifier: Programming Language :: Python :: 3.7
Classifier: Programming Language :: Python :: 3.8
Classifier: Programming Language :: Python :: 3.9
